vox8/__init__.py
vox8/client.py
vox8/py.typed
vox8-0.1.0.dist-info/METADATA
vox8-0.1.0.dist-info/WHEEL
vox8-0.1.0.dist-info/licenses/LICENSE
vox8-0.1.0.dist-info/RECORD
