Metadata-Version: 2.4
Name: vox8
Version: 0.1.0
Summary: Python SDK for vox8 real-time speech translation
Project-URL: Homepage, https://vox8.com
Project-URL: Documentation, https://vox8.com/docs
Project-URL: Repository, https://github.com/vox8-io/sdk-python
Project-URL: Issues, https://github.com/vox8-io/sdk-python/issues
Author-email: vox8 <support@vox8.com>
License-Expression: MIT
License-File: LICENSE
Keywords: real-time,speech,speech-to-speech,translation,voice,vox8,websocket
Classifier: Development Status :: 4 - Beta
Classifier: Intended Audience :: Developers
Classifier: License :: OSI Approved :: MIT License
Classifier: Programming Language :: Python :: 3
Classifier: Programming Language :: Python :: 3.9
Classifier: Programming Language :: Python :: 3.10
Classifier: Programming Language :: Python :: 3.11
Classifier: Programming Language :: Python :: 3.12
Classifier: Topic :: Multimedia :: Sound/Audio :: Speech
Requires-Python: >=3.9
Requires-Dist: websockets>=12.0
Provides-Extra: dev
Requires-Dist: mypy>=1.0; extra == 'dev'
Requires-Dist: pytest-asyncio>=0.21; extra == 'dev'
Requires-Dist: pytest>=7.0; extra == 'dev'
Requires-Dist: ruff>=0.1; extra == 'dev'
